[
  {
    "parsed_data": {
      "text": "SRIMATHI S  \nJunior Developer | Passionate About Coding and Problem Solving  D/O SAMINATHAN G  D no. 2 -298 \nAranganoor,  Mettur, Salem - \n636451 +91 6374164867  \nrajisrimathi2006@gmail.com  \nSRIMATHI S | LinkedIn  \n \n  \nEDUCATION   \nGovernment Higher Secondary School, Periyapatti   \n  \nSSLC : 100% (2021)  \n  \nHSC : 72.5% (2023)  \nK S Rangasamy College of Technology, Tiruchengode   \nB Tech Computer Science and Bussiness Systems  \nCGPA : 7.9 upto third semester (2023 - 2027)  \nPROJECTS   \nHospital Management System(CRUD)  \u2013 Build using Python and SQL .  \nAirline Reservation System \u2013 Build using java.    \n  \nTOOLS  \n  \nCanva  \nFigma  \nKinemaster   \n SKILLS  \n Java Programming.  \n R Programming.  \n Basic Python.  \n SQL Programming.  \n Exel.  \n Git and Github.  \n Basic HTML and CSS.  \nAWARDS  \n  \nInfosys - Certified Java Developer.  \n  \nCodeathon at KPRIET.  \n  \nInfosys - Basic Python.   \n  \nI regularly engage in coding on \nplatforms such as Leetcode and \ngfg.  \n  \nLANGUAGES  \n  \nTamil and English \n ",
      "email": "rajisrimathi2006@gmail.com",
      "phone": "+91 ",
      "skills": [
        "Python",
        "Java",
        "SQL",
        "Git",
        "HTML",
        "CSS"
      ],
      "education": [
        "K S Rangasamy College of Technology, Tiruchengode",
        "Kinemaster"
      ],
      "type": "resume"
    },
    "analysis": {
      "overall_score": 44.0,
      "detailed_scores": {
        "technical_score": 60,
        "experience_score": 0,
        "education_score": 50,
        "completeness_score": 100.0
      },
      "recommendations": [
        "Highlight more work experience and achievements"
      ]
    },
    "filename": "Copy_of_Resume.pdf",
    "_id": "5a426679-3ee1-459b-8f05-59c59accd17a",
    "created_at": "2025-09-07T11:07:50.491595"
  },
  {
    "parsed_data": {
      "text": "SRIMATHI S  \nJunior Developer | Passionate About Coding and Problem Solving  D/O SAMINATHAN G  D no. 2 -298 \nAranganoor,  Mettur, Salem - \n636451 +91 6374164867  \nrajisrimathi2006@gmail.com  \nSRIMATHI S | LinkedIn  \n \n  \nEDUCATION   \nGovernment Higher Secondary School, Periyapatti   \n  \nSSLC : 100% (2021)  \n  \nHSC : 72.5% (2023)  \nK S Rangasamy College of Technology, Tiruchengode   \nB Tech Computer Science and Bussiness Systems  \nCGPA : 7.9 upto third semester (2023 - 2027)  \nPROJECTS   \nHospital Management System(CRUD)  \u2013 Build using Python and SQL .  \nAirline Reservation System \u2013 Build using java.    \n  \nTOOLS  \n  \nCanva  \nFigma  \nKinemaster   \n SKILLS  \n Java Programming.  \n R Programming.  \n Basic Python.  \n SQL Programming.  \n Exel.  \n Git and Github.  \n Basic HTML and CSS.  \nAWARDS  \n  \nInfosys - Certified Java Developer.  \n  \nCodeathon at KPRIET.  \n  \nInfosys - Basic Python.   \n  \nI regularly engage in coding on \nplatforms such as Leetcode and \ngfg.  \n  \nLANGUAGES  \n  \nTamil and English \n ",
      "email": "rajisrimathi2006@gmail.com",
      "phone": "+91 ",
      "skills": [
        "Python",
        "Java",
        "SQL",
        "Git",
        "HTML",
        "CSS"
      ],
      "education": [
        "K S Rangasamy College of Technology, Tiruchengode",
        "Kinemaster"
      ],
      "type": "linkedin"
    },
    "analysis": {
      "overall_score": 44.0,
      "detailed_scores": {
        "technical_score": 60,
        "experience_score": 0,
        "education_score": 50,
        "completeness_score": 100.0
      },
      "recommendations": [
        "Highlight more work experience and achievements"
      ]
    },
    "filename": "Copy_of_Resume.pdf",
    "_id": "f30ff158-efe5-4824-8c68-34b0805d7e9c",
    "created_at": "2025-09-07T11:08:48.175675"
  },
  {
    "parsed_data": {
      "text": "SRIMATHI S  \nJunior Developer | Passionate About Coding and Problem Solving  D/O SAMINATHAN G  D no. 2 -298 \nAranganoor,  Mettur, Salem - \n636451 +91 6374164867  \nrajisrimathi2006@gmail.com  \nSRIMATHI S | LinkedIn  \n \n  \nEDUCATION   \nGovernment Higher Secondary School, Periyapatti   \n  \nSSLC : 100% (2021)  \n  \nHSC : 72.5% (2023)  \nK S Rangasamy College of Technology, Tiruchengode   \nB Tech Computer Science and Bussiness Systems  \nCGPA : 7.9 upto third semester (2023 - 2027)  \nPROJECTS   \nHospital Management System(CRUD)  \u2013 Build using Python and SQL .  \nAirline Reservation System \u2013 Build using java.    \n  \nTOOLS  \n  \nCanva  \nFigma  \nKinemaster   \n SKILLS  \n Java Programming.  \n R Programming.  \n Basic Python.  \n SQL Programming.  \n Exel.  \n Git and Github.  \n Basic HTML and CSS.  \nAWARDS  \n  \nInfosys - Certified Java Developer.  \n  \nCodeathon at KPRIET.  \n  \nInfosys - Basic Python.   \n  \nI regularly engage in coding on \nplatforms such as Leetcode and \ngfg.  \n  \nLANGUAGES  \n  \nTamil and English \n ",
      "email": "rajisrimathi2006@gmail.com",
      "phone": "+91 ",
      "skills": [
        "Python",
        "Java",
        "SQL",
        "Git",
        "HTML",
        "CSS"
      ],
      "education": [
        "K S Rangasamy College of Technology, Tiruchengode",
        "Kinemaster"
      ],
      "type": "linkedin"
    },
    "analysis": {
      "overall_score": 44.0,
      "detailed_scores": {
        "technical_score": 60,
        "experience_score": 0,
        "education_score": 50,
        "completeness_score": 100.0
      },
      "recommendations": [
        "Highlight more work experience and achievements"
      ]
    },
    "filename": "Copy_of_Resume.pdf",
    "_id": "9798ce26-59df-41a8-8b49-4e7ff9ae7b38",
    "created_at": "2025-09-07T11:09:10.794153"
  },
  {
    "parsed_data": {
      "text": "https://www.linkedin.com/in/srimathi -s-2942a4292  ",
      "email": null,
      "phone": null,
      "skills": [],
      "education": [],
      "type": "linkedin"
    },
    "analysis": {
      "overall_score": 0.0,
      "detailed_scores": {
        "technical_score": 0,
        "experience_score": 0,
        "education_score": 0,
        "completeness_score": 0.0
      },
      "recommendations": [
        "Add more technical skills relevant to your field",
        "Highlight more work experience and achievements",
        "Include educational background and certifications",
        "Complete missing contact information"
      ]
    },
    "filename": "linkedin.pdf",
    "_id": "2ab389cc-4f11-4d0c-a247-36b854f99f49",
    "created_at": "2025-09-07T11:11:15.184173"
  },
  {
    "parsed_data": {
      "profile_url": "https://www.linkedin.com/in/srimathi-s-2942a4292",
      "profile_id": "srimathi-s-2942a4292",
      "is_custom_url": true,
      "type": "linkedin_url"
    },
    "analysis": {
      "overall_score": 60,
      "detailed_scores": {
        "profile_completeness": 70,
        "url_optimization": 80,
        "accessibility": 75,
        "professional_branding": 65
      },
      "recommendations": [
        "Ensure your LinkedIn profile is public for better visibility",
        "Add a professional profile photo",
        "Write a compelling headline and summary",
        "List your skills and get endorsements",
        "Add work experience with detailed descriptions",
        "Include education and certifications",
        "Get recommendations from colleagues",
        "Post regular updates and articles"
      ]
    },
    "url": "https://www.linkedin.com/in/srimathi-s-2942a4292",
    "_id": "1f094485-47f2-4c8c-8b28-2503665e8421",
    "created_at": "2025-09-07T11:17:25.359736"
  },
  {
    "parsed_data": {
      "text": "SRIMATHI S  \nJunior Developer | Passionate About Coding and Problem Solving  D/O SAMINATHAN G  D no. 2 -298 \nAranganoor,  Mettur, Salem - \n636451 +91 6374164867  \nrajisrimathi2006@gmail.com  \nSRIMATHI S | LinkedIn  \n \n  \nEDUCATION   \nGovernment Higher Secondary School, Periyapatti   \n  \nSSLC : 100% (2021)  \n  \nHSC : 72.5% (2023)  \nK S Rangasamy College of Technology, Tiruchengode   \nB Tech Computer Science and Bussiness Systems  \nCGPA : 7.9 upto third semester (2023 - 2027)  \nPROJECTS   \nHospital Management System(CRUD)  \u2013 Build using Python and SQL .  \nAirline Reservation System \u2013 Build using java.    \n  \nTOOLS  \n  \nCanva  \nFigma  \nKinemaster   \n SKILLS  \n Java Programming.  \n R Programming.  \n Basic Python.  \n SQL Programming.  \n Exel.  \n Git and Github.  \n Basic HTML and CSS.  \nAWARDS  \n  \nInfosys - Certified Java Developer.  \n  \nCodeathon at KPRIET.  \n  \nInfosys - Basic Python.   \n  \nI regularly engage in coding on \nplatforms such as Leetcode and \ngfg.  \n  \nLANGUAGES  \n  \nTamil and English \n ",
      "email": "rajisrimathi2006@gmail.com",
      "phone": "+91 ",
      "skills": [
        "Python",
        "Java",
        "SQL",
        "Git",
        "HTML",
        "CSS"
      ],
      "education": [
        "K S Rangasamy College of Technology, Tiruchengode",
        "Kinemaster"
      ],
      "type": "resume"
    },
    "analysis": {
      "overall_score": 44.0,
      "detailed_scores": {
        "technical_score": 60,
        "experience_score": 0,
        "education_score": 50,
        "completeness_score": 100.0
      },
      "recommendations": [
        "Highlight more work experience and achievements"
      ]
    },
    "filename": "Copy_of_Resume.pdf",
    "_id": "753f6586-d3c3-448d-b6eb-f2a594de542e",
    "created_at": "2025-09-07T11:23:30.619258"
  },
  {
    "parsed_data": {
      "profile_url": "https://www.linkedin.com/in/srimathi-s-2942a4292",
      "profile_id": "srimathi-s-2942a4292",
      "is_custom_url": true,
      "type": "linkedin_url"
    },
    "analysis": {
      "overall_score": 60,
      "detailed_scores": {
        "profile_completeness": 70,
        "url_optimization": 80,
        "accessibility": 75,
        "professional_branding": 65
      },
      "recommendations": [
        "Ensure your LinkedIn profile is public for better visibility",
        "Add a professional profile photo",
        "Write a compelling headline and summary",
        "List your skills and get endorsements",
        "Add work experience with detailed descriptions",
        "Include education and certifications",
        "Get recommendations from colleagues",
        "Post regular updates and articles"
      ]
    },
    "url": "https://www.linkedin.com/in/srimathi-s-2942a4292",
    "_id": "829cbc89-946e-49b4-b35b-13f84ad3f4c1",
    "created_at": "2025-09-07T11:23:51.819225"
  },
  {
    "parsed_data": {
      "profile_url": "https://www.linkedin.com/in/srimathi-s-2942a4292",
      "profile_id": "srimathi-s-2942a4292",
      "is_custom_url": true,
      "type": "linkedin_url"
    },
    "analysis": {
      "overall_score": 60,
      "detailed_scores": {
        "profile_completeness": 70,
        "url_optimization": 80,
        "accessibility": 75,
        "professional_branding": 65
      },
      "recommendations": [
        "Ensure your LinkedIn profile is public for better visibility",
        "Add a professional profile photo",
        "Write a compelling headline and summary",
        "List your skills and get endorsements",
        "Add work experience with detailed descriptions",
        "Include education and certifications",
        "Get recommendations from colleagues",
        "Post regular updates and articles"
      ]
    },
    "url": "https://www.linkedin.com/in/srimathi-s-2942a4292",
    "_id": "86b99c41-1fe3-4074-8a63-7d0216b6a72b",
    "created_at": "2025-09-07T11:28:34.870899"
  },
  {
    "parsed_data": {
      "text": "SRIMATHI S  \nJunior Developer | Passionate About Coding and Problem Solving  D/O SAMINATHAN G  D no. 2 -298 \nAranganoor,  Mettur, Salem - \n636451 +91 6374164867  \nrajisrimathi2006@gmail.com  \nSRIMATHI S | LinkedIn  \n \n  \nEDUCATION   \nGovernment Higher Secondary School, Periyapatti   \n  \nSSLC : 100% (2021)  \n  \nHSC : 72.5% (2023)  \nK S Rangasamy College of Technology, Tiruchengode   \nB Tech Computer Science and Bussiness Systems  \nCGPA : 7.9 upto third semester (2023 - 2027)  \nPROJECTS   \nHospital Management System(CRUD)  \u2013 Build using Python and SQL .  \nAirline Reservation System \u2013 Build using java.    \n  \nTOOLS  \n  \nCanva  \nFigma  \nKinemaster   \n SKILLS  \n Java Programming.  \n R Programming.  \n Basic Python.  \n SQL Programming.  \n Exel.  \n Git and Github.  \n Basic HTML and CSS.  \nAWARDS  \n  \nInfosys - Certified Java Developer.  \n  \nCodeathon at KPRIET.  \n  \nInfosys - Basic Python.   \n  \nI regularly engage in coding on \nplatforms such as Leetcode and \ngfg.  \n  \nLANGUAGES  \n  \nTamil and English \n ",
      "email": "rajisrimathi2006@gmail.com",
      "phone": "+91 ",
      "skills": [
        "Python",
        "Java",
        "SQL",
        "Git",
        "HTML",
        "CSS"
      ],
      "education": [
        "K S Rangasamy College of Technology, Tiruchengode",
        "Kinemaster"
      ],
      "type": "resume"
    },
    "analysis": {
      "overall_score": 44.0,
      "detailed_scores": {
        "technical_score": 60,
        "experience_score": 0,
        "education_score": 50,
        "completeness_score": 100.0
      },
      "recommendations": [
        "Highlight more work experience and achievements"
      ]
    },
    "filename": "Copy_of_Resume.pdf",
    "_id": "55791f64-da1e-4ac7-865a-1f001881f3eb",
    "created_at": "2025-09-07T11:28:49.719374"
  },
  {
    "parsed_data": {
      "text": "SRIMATHI S  \nJunior Developer | Passionate About Coding and Problem Solving  D/O SAMINATHAN G  D no. 2 -298 \nAranganoor,  Mettur, Salem - \n636451 +91 6374164867  \nrajisrimathi2006@gmail.com  \nSRIMATHI S | LinkedIn  \n \n  \nEDUCATION   \nGovernment Higher Secondary School, Periyapatti   \n  \nSSLC : 100% (2021)  \n  \nHSC : 72.5% (2023)  \nK S Rangasamy College of Technology, Tiruchengode   \nB Tech Computer Science and Bussiness Systems  \nCGPA : 7.9 upto third semester (2023 - 2027)  \nPROJECTS   \nHospital Management System(CRUD)  \u2013 Build using Python and SQL .  \nAirline Reservation System \u2013 Build using java.    \n  \nTOOLS  \n  \nCanva  \nFigma  \nKinemaster   \n SKILLS  \n Java Programming.  \n R Programming.  \n Basic Python.  \n SQL Programming.  \n Exel.  \n Git and Github.  \n Basic HTML and CSS.  \nAWARDS  \n  \nInfosys - Certified Java Developer.  \n  \nCodeathon at KPRIET.  \n  \nInfosys - Basic Python.   \n  \nI regularly engage in coding on \nplatforms such as Leetcode and \ngfg.  \n  \nLANGUAGES  \n  \nTamil and English \n ",
      "email": "rajisrimathi2006@gmail.com",
      "phone": "+91 ",
      "skills": [
        "Python",
        "Java",
        "SQL",
        "Git",
        "HTML",
        "CSS"
      ],
      "education": [
        "K S Rangasamy College of Technology, Tiruchengode",
        "Kinemaster"
      ],
      "type": "resume"
    },
    "analysis": {
      "overall_score": 44.0,
      "detailed_scores": {
        "technical_score": 60,
        "experience_score": 0,
        "education_score": 50,
        "completeness_score": 100.0
      },
      "recommendations": [
        "Highlight more work experience and achievements"
      ]
    },
    "filename": "Copy_of_Resume.pdf",
    "_id": "a9d8f947-82e6-4236-b7da-1d14c938bfc4",
    "created_at": "2025-09-08T03:33:21.411135"
  },
  {
    "parsed_data": {
      "text": "SRIMATHI S Email : rajisrimathi2006@gmail.com\nLinkedIn Mobile : +91-6374164867\nProfessional Summary\nAspiring Full Stack Web Developer with hands-on experience in building interactive web pages using HTML, CSS,\nJavaScript, and React.js. Familiar with backend development using Node.js and MongoDB, with strong academic\nexposure to Java programming and Database Management Systems (DBMS). Actively working on real-time projects such\nas an online grocery shop and a personal portfolio website. Eager to contribute to real-world development teams while\ncontinuously learning and improving backend and full stack capabilities. A fast learner with strong problem-solving skills\nand the ability to work independently or in collaborative environments.\nExperience\n\u2022Personal Projects / Academic Work Tiruchengode, India (Remote)\nFull Stack Web Developer (Trainee) July 2025 \u2013 Present\n\u25e6Grocery Shop Website : Developed a full-stack grocery shopping website using HTML, CSS, JavaScript, React.js for the\nfrontend, and Node.js with MongoDB for backend. Included features like product listings, customer contact form, and admin\ndashboard.\n\u25e6Power BI : Developed and implemented a Spotify Dashboard using Power BI to visualize music data and insights.\n\u25e6Python + DBMS Academic Projects : Built mini-projects simulating real-time CRUD operations. Designed normalized\ndatabase schemas and performed SQL queries using MySQL.\n\u25e6Portfolio Website (Ongoing) : Building a personal portfolio using React.js and Tailwind CSS. Includes animated skill\nprogress bars, project showcase, contact section, and downloadable resume.\nCertifications / Personal Projects\n\u2022Certifications :\n\u25e6NPTEL Certification in Internet of Things (IoT) \u2013 Silver + Elite\n\u25e6NPTEL Certification in Python Programming\n\u25e6Infosys Certification in Python Full Stack Development\n\u25e6Infosys Certification in Java with Data Structures\n\u25e6Web Development Bootcamp \u2013 Coursera\n\u25e6MongoDB Basics \u2013 Great Learning\n\u2022Personal Projects :\n\u25e6Grocery Shop Website \u2013 Full stack website built using React.js, Node.js, Express.js, and MongoDB. Includes product\nlisting, contact form, and admin dashboard.\n\u25e6Portfolio Website (In Progress) \u2013 Personal portfolio site using React.js and Tailwind CSS with animated skill bars and\ndownloadable resume.\n\u25e6Airline Reservation System (Java) \u2013 Simulates flight booking and management using object-oriented programming in\nJava.\n\u25e6Hospital Management System (DBMS) \u2013 CRUD-based database project implementing hospital records using MySQL\nand basic UI.\nEducation\n\u2022K.S. Rangasamy College of Technology, Tiruchengode Tamil Nadu, IN\nB.Tech in Computer Science and Business Systems (CSBS); CGPA: 8.0 (upto 3rd semester) August 2025 \u2013 Present\n\u2022Government Higher Secondary School, Periyapatti Tamil Nadu, IN\nHigher Secondary Certificate (HSC); Percentage: 72.5% 2022 \u2013 2023\n\u2022Government Higher Secondary School, Periyapatti Tamil Nadu, IN\nSecondary School Leaving Certificate (SSLC); Percentage: 100% 2020 \u2013 2021",
      "email": "rajisrimathi2006@gmail.com",
      "phone": "+91-",
      "skills": [
        "Python",
        "JavaScript",
        "Java",
        "React",
        "Node.js",
        "SQL",
        "MongoDB",
        "HTML",
        "CSS",
        "Express",
        "MySQL"
      ],
      "education": [
        "\u2022K.S. Rangasamy College of Technology, Tiruchengode Tamil Nadu, IN"
      ],
      "type": "resume"
    },
    "analysis": {
      "overall_score": 55.0,
      "detailed_scores": {
        "technical_score": 100,
        "experience_score": 0,
        "education_score": 25,
        "completeness_score": 100.0
      },
      "recommendations": [
        "Highlight more work experience and achievements",
        "Include educational background and certifications"
      ]
    },
    "filename": "resume2.pdf",
    "_id": "55134f9d-d0f4-4bd9-b677-4f31835fefc6",
    "created_at": "2025-09-08T03:34:14.808560"
  },
  {
    "parsed_data": {
      "text": "SRIMATHI S Email : rajisrimathi2006@gmail.com\nLinkedIn Mobile : +91-6374164867\nProfessional Summary\nAspiring Full Stack Web Developer with hands-on experience in building interactive web pages using HTML, CSS,\nJavaScript, and React.js. Familiar with backend development using Node.js and MongoDB, with strong academic\nexposure to Java programming and Database Management Systems (DBMS). Actively working on real-time projects such\nas an online grocery shop and a personal portfolio website. Eager to contribute to real-world development teams while\ncontinuously learning and improving backend and full stack capabilities. A fast learner with strong problem-solving skills\nand the ability to work independently or in collaborative environments.\nExperience\n\u2022Personal Projects / Academic Work Tiruchengode, India (Remote)\nFull Stack Web Developer (Trainee) July 2025 \u2013 Present\n\u25e6Grocery Shop Website : Developed a full-stack grocery shopping website using HTML, CSS, JavaScript, React.js for the\nfrontend, and Node.js with MongoDB for backend. Included features like product listings, customer contact form, and admin\ndashboard.\n\u25e6Admin Query Dashboard : Implemented an admin panel to view and respond to customer queries submitted through the\ncontact form. Utilized Express.js and MongoDB to fetch and manage data securely.\n\u25e6Java + DBMS Academic Projects : Created mini projects simulating OS concepts like FCFS Scheduling, Page\nReplacement (FIFO, LRU), and Disk Scheduling using Java. Designed normalized database schemas and executed SQL\nqueries in MySQL.\n\u25e6Portfolio Website (Ongoing) : Building a personal portfolio using React.js and Tailwind CSS. Includes animated skill\nprogress bars, project showcase, contact section, and downloadable resume.\nCertifications / Personal Projects\n\u2022Certifications :\n\u25e6NPTEL Certification in Internet of Things (IoT) \u2013 Silver + Elite\n\u25e6NPTEL Certification in Python Programming\n\u25e6Infosys Certification in Python Full Stack Development\n\u25e6Infosys Certification in Java with Data Structures\n\u25e6Web Development Bootcamp \u2013 Coursera\n\u25e6MongoDB Basics \u2013 Great Learning\n\u2022Personal Projects :\n\u25e6Grocery Shop Website \u2013 Full stack website built using React.js, Node.js, Express.js, and MongoDB. Includes product\nlisting, contact form, and admin dashboard.\n\u25e6Portfolio Website (In Progress) \u2013 Personal portfolio site using React.js and Tailwind CSS with animated skill bars and\ndownloadable resume.\n\u25e6Airline Reservation System (Java) \u2013 Simulates flight booking and management using object-oriented programming in\nJava.\n\u25e6Hospital Management System (DBMS) \u2013 CRUD-based database project implementing hospital records using MySQL\nand basic UI.\nEducation\n\u2022K.S. Rangasamy College of Technology, Tiruchengode Tamil Nadu, IN\nB.Tech in Computer Science and Business Systems (CSBS); CGPA: 8.0 (upto 3rd semester) August 2025 \u2013 Present\n\u2022Government Higher Secondary School, Periyapatti Tamil Nadu, IN\nHigher Secondary Certificate (HSC); Percentage: 72.5% 2022 \u2013 2023\n\u2022Government Higher Secondary School, Periyapatti Tamil Nadu, IN\nSecondary School Leaving Certificate (SSLC); Percentage: 100% 2020 \u2013 2021",
      "email": "rajisrimathi2006@gmail.com",
      "phone": "+91-",
      "skills": [
        "Python",
        "JavaScript",
        "Java",
        "React",
        "Node.js",
        "SQL",
        "MongoDB",
        "HTML",
        "CSS",
        "Express",
        "MySQL"
      ],
      "education": [
        "\u2022K.S. Rangasamy College of Technology, Tiruchengode Tamil Nadu, IN"
      ],
      "type": "resume"
    },
    "analysis": {
      "overall_score": 55.0,
      "detailed_scores": {
        "technical_score": 100,
        "experience_score": 0,
        "education_score": 25,
        "completeness_score": 100.0
      },
      "recommendations": [
        "Highlight more work experience and achievements",
        "Include educational background and certifications"
      ]
    },
    "filename": "Anti_CV.pdf",
    "_id": "fce2bedd-0567-4739-8ced-63ee93ea511e",
    "created_at": "2025-09-08T03:34:46.335040"
  },
  {
    "parsed_data": {
      "text": "SRIMATHI S Email : rajisrimathi2006@gmail.com\nlinkedin : linkedin.com/in/srimathi-s-2942a4292 Mobile : +91-6374164867\nProfessional Summary\nAspiring Full Stack Web Developer with hands-on experience in building responsive webapplications using HTML, CSS,\nJavaScript, React, Node.js, and MongoDB. Built and de-ployed projects like an online grocery shop and a personal\nportfolio. Eager to learn newtechnologies and solve real-world problems.\nEducation\n\u2022K.S. Rangasamy College of Technology, Tiruchengode Tamil Nadu, IN\nB.Tech in Computer Science and Business Systems (CSBS); CGPA: 7.9 (upto 3rd semester) August 2025 \u2013 Present\n\u2022Government Higher Secondary School, Periyapatti Tamil Nadu, IN\nHigher Secondary Certificate (HSC); Percentage: 72.5% 2022 \u2013 2023\n\u2022Government Higher Secondary School, Periyapatti Tamil Nadu, IN\nSecondary School Leaving Certificate (SSLC); Percentage: 100% 2020 \u2013 2021\nArea of Interest\n\u2022Technical Skills: HTML, CSS, JavaScript, React.js, Node.js, Express.js, MongoDB, MySQL, Power BI\n\u2022Soft Skills: Problem Solving, Communication, Team Collaboration, Adaptability\nExperience\n\u2022Personal Projects / Academic Work Tiruchengode, India (Remote)\nFull Stack Web Developer (Trainee) July 2025 \u2013 Present\n\u25e6Grocery Shop Website : Developed a full-stack grocery shopping website using HTML, CSS, JavaScript, React.js for the\nfrontend, and Node.js with MongoDB for backend. Included features like product listings, customer contact form, and admin\ndashboard.\n\u25e6Power BI : Developed and implemented a Spotify Dashboard using Power BI to visualize music data and insights.\n\u25e6Python + DBMS Academic Projects : Built mini-projects simulating real-time CRUD operations. Designed normalized\ndatabase schemas and performed SQL queries using MySQL.\n\u25e6Portfolio Website (Ongoing) : Building a personal portfolio using React.js and Tailwind CSS. Includes animated skill\nprogress bars, project showcase, contact section, and downloadable resume.\nCertifications / Personal Projects\n\u2022Certifications :\n\u25e6NPTEL Certification in Internet of Things (IoT) \u2013 Silver + Elite\n\u25e6NPTEL Certification in Python Programming\n\u25e6Infosys Certification in Python Full Stack Development\n\u25e6Infosys Certification in Java with Data Structures\n\u2022Personal Projects :\n\u25e6Grocery Shop Website \u2013 Full stack website built using React.js, Node.js, Express.js, and MongoDB. Includes product\nlisting, contact form, and admin dashboard.\n\u25e6Portfolio Website (In Progress) \u2013 Personal portfolio site using React.js and Tailwind CSS with animated skill bars and\ndownloadable resume.\n\u25e6Airline Reservation System (Java) \u2013 Simulates flight booking and management using object-oriented programming in\nJava.\n\u25e6Hospital Management System (DBMS) \u2013 CRUD-based database project implementing hospital records using MySQL\nand basic UI.",
      "email": "rajisrimathi2006@gmail.com",
      "phone": "+91-",
      "skills": [
        "Python",
        "JavaScript",
        "Java",
        "React",
        "Node.js",
        "SQL",
        "MongoDB",
        "HTML",
        "CSS",
        "Express",
        "MySQL"
      ],
      "education": [
        "linkedin : linkedin.com/in/srimathi-s-2942a4292 Mobile : +91-6374164867",
        "Professional Summary",
        "Aspiring Full Stack Web Developer with hands-on experience in building responsive webapplications using HTML, CSS,",
        "portfolio. Eager to learn newtechnologies and solve real-world problems.",
        "Education"
      ],
      "type": "resume"
    },
    "analysis": {
      "overall_score": 65.0,
      "detailed_scores": {
        "technical_score": 100,
        "experience_score": 0,
        "education_score": 75,
        "completeness_score": 100.0
      },
      "recommendations": [
        "Highlight more work experience and achievements"
      ]
    },
    "filename": "resume.pdf",
    "_id": "abcba794-2a36-44c4-8a9d-f572c100ac77",
    "created_at": "2025-09-08T03:43:24.467906"
  },
  {
    "parsed_data": {
      "text": "SRIMATHI S Email : rajisrimathi2006@gmail.com\nLinkedIn Mobile : +91-6374164867\nProfessional Summary\nAspiring Full Stack Web Developer with hands-on experience in building interactive web pages using HTML, CSS,\nJavaScript, and React.js. Familiar with backend development using Node.js and MongoDB, with strong academic\nexposure to Java programming and Database Management Systems (DBMS). Actively working on real-time projects such\nas an online grocery shop and a personal portfolio website. Eager to contribute to real-world development teams while\ncontinuously learning and improving backend and full stack capabilities. A fast learner with strong problem-solving skills\nand the ability to work independently or in collaborative environments.\nExperience\n\u2022Personal Projects / Academic Work Tiruchengode, India (Remote)\nFull Stack Web Developer (Trainee) July 2025 \u2013 Present\n\u25e6Grocery Shop Website : Developed a full-stack grocery shopping website using HTML, CSS, JavaScript, React.js for the\nfrontend, and Node.js with MongoDB for backend. Included features like product listings, customer contact form, and admin\ndashboard.\n\u25e6Power BI : Developed and implemented a Spotify Dashboard using Power BI to visualize music data and insights.\n\u25e6Python + DBMS Academic Projects : Built mini-projects simulating real-time CRUD operations. Designed normalized\ndatabase schemas and performed SQL queries using MySQL.\n\u25e6Portfolio Website (Ongoing) : Building a personal portfolio using React.js and Tailwind CSS. Includes animated skill\nprogress bars, project showcase, contact section, and downloadable resume.\nCertifications / Personal Projects\n\u2022Certifications :\n\u25e6NPTEL Certification in Internet of Things (IoT) \u2013 Silver + Elite\n\u25e6NPTEL Certification in Python Programming\n\u25e6Infosys Certification in Python Full Stack Development\n\u25e6Infosys Certification in Java with Data Structures\n\u25e6Web Development Bootcamp \u2013 Coursera\n\u25e6MongoDB Basics \u2013 Great Learning\n\u2022Personal Projects :\n\u25e6Grocery Shop Website \u2013 Full stack website built using React.js, Node.js, Express.js, and MongoDB. Includes product\nlisting, contact form, and admin dashboard.\n\u25e6Portfolio Website (In Progress) \u2013 Personal portfolio site using React.js and Tailwind CSS with animated skill bars and\ndownloadable resume.\n\u25e6Airline Reservation System (Java) \u2013 Simulates flight booking and management using object-oriented programming in\nJava.\n\u25e6Hospital Management System (DBMS) \u2013 CRUD-based database project implementing hospital records using MySQL\nand basic UI.\nEducation\n\u2022K.S. Rangasamy College of Technology, Tiruchengode Tamil Nadu, IN\nB.Tech in Computer Science and Business Systems (CSBS); CGPA: 8.0 (upto 3rd semester) August 2025 \u2013 Present\n\u2022Government Higher Secondary School, Periyapatti Tamil Nadu, IN\nHigher Secondary Certificate (HSC); Percentage: 72.5% 2022 \u2013 2023\n\u2022Government Higher Secondary School, Periyapatti Tamil Nadu, IN\nSecondary School Leaving Certificate (SSLC); Percentage: 100% 2020 \u2013 2021",
      "email": "rajisrimathi2006@gmail.com",
      "phone": "+91-6374164867",
      "skills": [
        "Python",
        "JavaScript",
        "Java",
        "React",
        "Node.js",
        "SQL",
        "MongoDB",
        "HTML",
        "CSS",
        "Express",
        "MySQL"
      ],
      "education": [
        "CGPA: 8.0",
        "CGPA: 8.0",
        "Percentage: 72.5%",
        "Percentage: 72.5%",
        "B.Tech in Computer Science and Business Systems (CSBS); CGPA: 8.0 (upto 3rd semester) August 2025 \u2013 Present"
      ],
      "type": "resume"
    },
    "analysis": {
      "overall_score": 64.0,
      "detailed_scores": {
        "technical_score": 100,
        "experience_score": 0,
        "education_score": 70,
        "completeness_score": 100.0
      },
      "recommendations": [
        "Highlight more work experience and achievements"
      ]
    },
    "filename": "resume2.pdf",
    "_id": "63c425b2-28c8-416f-8f65-561eca8fc93a",
    "created_at": "2025-09-08T03:49:48.061021"
  },
  {
    "parsed_data": {
      "profile_url": "https://www.linkedin.com/in/srimathi-s-2942a4292",
      "profile_id": "srimathi-s-2942a4292",
      "is_custom_url": true,
      "type": "linkedin_url"
    },
    "analysis": {
      "overall_score": 60,
      "detailed_scores": {
        "profile_completeness": 70,
        "url_optimization": 80,
        "accessibility": 75,
        "professional_branding": 65
      },
      "recommendations": [
        "Ensure your LinkedIn profile is public for better visibility",
        "Add a professional profile photo",
        "Write a compelling headline and summary",
        "List your skills and get endorsements",
        "Add work experience with detailed descriptions",
        "Include education and certifications",
        "Get recommendations from colleagues",
        "Post regular updates and articles"
      ]
    },
    "url": "https://www.linkedin.com/in/srimathi-s-2942a4292",
    "_id": "763cec7e-1ce2-4d81-af5c-f47ca7fe089c",
    "created_at": "2025-09-08T03:51:57.421753"
  },
  {
    "parsed_data": {
      "profile_url": "https://www.linkedin.com/in/srimathi-s-2942a4292",
      "certificates": {
        "total_certificates": 3,
        "recent_certificates": [],
        "trending_skills": [
          "Cloud Computing",
          "Data Science"
        ]
      },
      "activity": {
        "post_frequency": 3,
        "engagement_level": "Medium",
        "content_quality": "Moderate"
      },
      "type": "linkedin_url"
    },
    "analysis": {
      "overall_score": 80,
      "detailed_scores": {
        "certificates_and_skills": 20,
        "activity_and_engagement": 20,
        "professional_networking": 20,
        "profile_completeness": 20
      },
      "certificates_analysis": {
        "total_certificates": 3,
        "recent_certificates": [],
        "trending_skills": [
          "Cloud Computing",
          "Data Science"
        ]
      },
      "activity_analysis": {
        "post_frequency": 3,
        "engagement_level": "Medium",
        "content_quality": "Moderate"
      },
      "recommendations": [
        "Obtain recent certifications to show continuous learning",
        "Increase your posting frequency to improve visibility and engagement",
        "Share more professional content about your projects and achievements",
        "Share industry insights and thought leadership content",
        "Engage with others' posts through meaningful comments",
        "Update your profile regularly with new achievements",
        "Join relevant professional groups and participate in discussions"
      ]
    },
    "url": "https://www.linkedin.com/in/srimathi-s-2942a4292",
    "_id": "ce1f58db-77fa-45bf-bf53-369372558c05",
    "created_at": "2025-09-08T03:59:26.545810"
  },
  {
    "parsed_data": {
      "text": "SRIMATHI S Email : rajisrimathi2006@gmail.com\nlinkedin : linkedin.com/in/srimathi-s-2942a4292 Mobile : +91-6374164867\nProfessional Summary\nAspiring Full Stack Web Developer with hands-on experience in building responsive webapplications using HTML, CSS,\nJavaScript, React, Node.js, and MongoDB. Built and de-ployed projects like an online grocery shop and a personal\nportfolio. Eager to learn newtechnologies and solve real-world problems.\nEducation\n\u2022K.S. Rangasamy College of Technology, Tiruchengode Tamil Nadu, IN\nB.Tech in Computer Science and Business Systems (CSBS); CGPA: 7.9 (upto 3rd semester) August 2025 \u2013 Present\n\u2022Government Higher Secondary School, Periyapatti Tamil Nadu, IN\nHigher Secondary Certificate (HSC); Percentage: 72.5% 2022 \u2013 2023\n\u2022Government Higher Secondary School, Periyapatti Tamil Nadu, IN\nSecondary School Leaving Certificate (SSLC); Percentage: 100% 2020 \u2013 2021\nArea of Interest\n\u2022Technical Skills: HTML, CSS, JavaScript, React.js, Node.js, Express.js, MongoDB, MySQL, Power BI\n\u2022Soft Skills: Problem Solving, Communication, Team Collaboration, Adaptability\nExperience\n\u2022Personal Projects / Academic Work Tiruchengode, India (Remote)\nFull Stack Web Developer (Trainee) July 2025 \u2013 Present\n\u25e6Grocery Shop Website : Developed a full-stack grocery shopping website using HTML, CSS, JavaScript, React.js for the\nfrontend, and Node.js with MongoDB for backend. Included features like product listings, customer contact form, and admin\ndashboard.\n\u25e6Power BI : Developed and implemented a Spotify Dashboard using Power BI to visualize music data and insights.\n\u25e6Python + DBMS Academic Projects : Built mini-projects simulating real-time CRUD operations. Designed normalized\ndatabase schemas and performed SQL queries using MySQL.\n\u25e6Portfolio Website (Ongoing) : Building a personal portfolio using React.js and Tailwind CSS. Includes animated skill\nprogress bars, project showcase, contact section, and downloadable resume.\nCertifications / Personal Projects\n\u2022Certifications :\n\u25e6NPTEL Certification in Internet of Things (IoT) \u2013 Silver + Elite\n\u25e6NPTEL Certification in Python Programming\n\u25e6Infosys Certification in Python Full Stack Development\n\u25e6Infosys Certification in Java with Data Structures\n\u2022Personal Projects :\n\u25e6Grocery Shop Website \u2013 Full stack website built using React.js, Node.js, Express.js, and MongoDB. Includes product\nlisting, contact form, and admin dashboard.\n\u25e6Portfolio Website (In Progress) \u2013 Personal portfolio site using React.js and Tailwind CSS with animated skill bars and\ndownloadable resume.\n\u25e6Airline Reservation System (Java) \u2013 Simulates flight booking and management using object-oriented programming in\nJava.\n\u25e6Hospital Management System (DBMS) \u2013 CRUD-based database project implementing hospital records using MySQL\nand basic UI.",
      "email": "rajisrimathi2006@gmail.com",
      "phone": "+91-6374164867",
      "skills": [
        "Python",
        "JavaScript",
        "Java",
        "React",
        "Node.js",
        "SQL",
        "MongoDB",
        "HTML",
        "CSS",
        "Express",
        "MySQL"
      ],
      "education": [
        "CGPA: 7.9",
        "CGPA: 7.9",
        "Percentage: 72.5%",
        "Percentage: 72.5%",
        "B.Tech in Computer Science and Business Systems (CSBS); CGPA: 7.9 (upto 3rd semester) August 2025 \u2013 Present"
      ],
      "type": "resume"
    },
    "analysis": {
      "overall_score": 63.0,
      "detailed_scores": {
        "technical_score": 100,
        "experience_score": 0,
        "education_score": 65,
        "completeness_score": 100.0
      },
      "recommendations": [
        "Highlight more work experience and achievements"
      ]
    },
    "filename": "resume.pdf",
    "_id": "e814975d-b425-46a7-a05e-8406d60788a4",
    "created_at": "2025-09-08T04:07:35.771121"
  },
  {
    "parsed_data": {
      "profile_url": "https://www.linkedin.com/in/srimathi-s-2942a4292",
      "certificates": {
        "total_certificates": 3,
        "recent_certificates": [],
        "trending_skills": [
          "Cloud Computing",
          "Data Science"
        ]
      },
      "activity": {
        "post_frequency": 3,
        "engagement_level": "Medium",
        "content_quality": "Moderate"
      },
      "type": "linkedin_url"
    },
    "analysis": {
      "overall_score": 80,
      "detailed_scores": {
        "certificates_and_skills": 20,
        "activity_and_engagement": 20,
        "professional_networking": 20,
        "profile_completeness": 20
      },
      "certificates_analysis": {
        "total_certificates": 3,
        "recent_certificates": [],
        "trending_skills": [
          "Cloud Computing",
          "Data Science"
        ]
      },
      "activity_analysis": {
        "post_frequency": 3,
        "engagement_level": "Medium",
        "content_quality": "Moderate"
      },
      "recommendations": [
        "Obtain recent certifications to show continuous learning",
        "Increase your posting frequency to improve visibility and engagement",
        "Share more professional content about your projects and achievements",
        "Share industry insights and thought leadership content",
        "Engage with others' posts through meaningful comments",
        "Update your profile regularly with new achievements",
        "Join relevant professional groups and participate in discussions"
      ]
    },
    "url": "https://www.linkedin.com/in/srimathi-s-2942a4292",
    "_id": "1c0b2737-8d97-477f-a275-d88e678caeff",
    "created_at": "2025-09-08T04:08:09.294600"
  },
  {
    "parsed_data": {
      "profile_url": "https://www.linkedin.com/in/srimathi-s-2942a4292",
      "certificates": {
        "total_certificates": 3,
        "recent_certificates": [],
        "trending_skills": [
          "Cloud Computing",
          "Data Science"
        ]
      },
      "activity": {
        "post_frequency": 3,
        "engagement_level": "Medium",
        "content_quality": "Moderate"
      },
      "type": "linkedin_url"
    },
    "analysis": {
      "overall_score": 80,
      "detailed_scores": {
        "certificates_and_skills": 20,
        "activity_and_engagement": 20,
        "professional_networking": 20,
        "profile_completeness": 20
      },
      "certificates_analysis": {
        "total_certificates": 3,
        "recent_certificates": [],
        "trending_skills": [
          "Cloud Computing",
          "Data Science"
        ]
      },
      "activity_analysis": {
        "post_frequency": 3,
        "engagement_level": "Medium",
        "content_quality": "Moderate"
      },
      "recommendations": [
        "Obtain recent certifications to show continuous learning",
        "Increase your posting frequency to improve visibility and engagement",
        "Share more professional content about your projects and achievements",
        "Share industry insights and thought leadership content",
        "Engage with others' posts through meaningful comments",
        "Update your profile regularly with new achievements",
        "Join relevant professional groups and participate in discussions"
      ]
    },
    "url": "https://www.linkedin.com/in/srimathi-s-2942a4292",
    "_id": "b061fa83-e7f9-4b25-9be1-8b923ca713fa",
    "created_at": "2025-09-08T04:08:26.906950"
  },
  {
    "parsed_data": {
      "text": "SRIMATHI S Email : rajisrimathi2006@gmail.com\nLinkedIn Mobile : +91-6374164867\nProfessional Summary\nAspiring Full Stack Web Developer with hands-on experience in building interactive web pages using HTML, CSS,\nJavaScript, and React.js. Familiar with backend development using Node.js and MongoDB, with strong academic\nexposure to Java programming and Database Management Systems (DBMS). Actively working on real-time projects such\nas an online grocery shop and a personal portfolio website. Eager to contribute to real-world development teams while\ncontinuously learning and improving backend and full stack capabilities. A fast learner with strong problem-solving skills\nand the ability to work independently or in collaborative environments.\nExperience\n\u2022Personal Projects / Academic Work Tiruchengode, India (Remote)\nFull Stack Web Developer (Trainee) July 2025 \u2013 Present\n\u25e6Grocery Shop Website : Developed a full-stack grocery shopping website using HTML, CSS, JavaScript, React.js for the\nfrontend, and Node.js with MongoDB for backend. Included features like product listings, customer contact form, and admin\ndashboard.\n\u25e6Power BI : Developed and implemented a Spotify Dashboard using Power BI to visualize music data and insights.\n\u25e6Python + DBMS Academic Projects : Built mini-projects simulating real-time CRUD operations. Designed normalized\ndatabase schemas and performed SQL queries using MySQL.\n\u25e6Portfolio Website (Ongoing) : Building a personal portfolio using React.js and Tailwind CSS. Includes animated skill\nprogress bars, project showcase, contact section, and downloadable resume.\nCertifications / Personal Projects\n\u2022Certifications :\n\u25e6NPTEL Certification in Internet of Things (IoT) \u2013 Silver + Elite\n\u25e6NPTEL Certification in Python Programming\n\u25e6Infosys Certification in Python Full Stack Development\n\u25e6Infosys Certification in Java with Data Structures\n\u25e6Web Development Bootcamp \u2013 Coursera\n\u25e6MongoDB Basics \u2013 Great Learning\n\u2022Personal Projects :\n\u25e6Grocery Shop Website \u2013 Full stack website built using React.js, Node.js, Express.js, and MongoDB. Includes product\nlisting, contact form, and admin dashboard.\n\u25e6Portfolio Website (In Progress) \u2013 Personal portfolio site using React.js and Tailwind CSS with animated skill bars and\ndownloadable resume.\n\u25e6Airline Reservation System (Java) \u2013 Simulates flight booking and management using object-oriented programming in\nJava.\n\u25e6Hospital Management System (DBMS) \u2013 CRUD-based database project implementing hospital records using MySQL\nand basic UI.\nEducation\n\u2022K.S. Rangasamy College of Technology, Tiruchengode Tamil Nadu, IN\nB.Tech in Computer Science and Business Systems (CSBS); CGPA: 8.0 (upto 3rd semester) August 2025 \u2013 Present\n\u2022Government Higher Secondary School, Periyapatti Tamil Nadu, IN\nHigher Secondary Certificate (HSC); Percentage: 72.5% 2022 \u2013 2023\n\u2022Government Higher Secondary School, Periyapatti Tamil Nadu, IN\nSecondary School Leaving Certificate (SSLC); Percentage: 100% 2020 \u2013 2021",
      "email": "rajisrimathi2006@gmail.com",
      "phone": "+91-6374164867",
      "skills": [
        "Python",
        "JavaScript",
        "Java",
        "React",
        "Node.js",
        "SQL",
        "MongoDB",
        "HTML",
        "CSS",
        "Express",
        "MySQL"
      ],
      "education": [
        "CGPA: 8.0",
        "CGPA: 8.0",
        "Percentage: 72.5%",
        "Percentage: 72.5%",
        "B.Tech in Computer Science and Business Systems (CSBS); CGPA: 8.0 (upto 3rd semester) August 2025 \u2013 Present"
      ],
      "type": "resume"
    },
    "analysis": {
      "overall_score": 64.0,
      "detailed_scores": {
        "technical_score": 100,
        "experience_score": 0,
        "education_score": 70,
        "completeness_score": 100.0
      },
      "recommendations": [
        "Highlight more work experience and achievements"
      ]
    },
    "filename": "resume2.pdf",
    "_id": "3e038a65-1e96-4ccb-ad90-4650ccd9f93e",
    "created_at": "2025-09-08T04:28:00.169142"
  },
  {
    "parsed_data": {
      "profile_url": "https://www.linkedin.com/in/srimathi-s-2942a4292",
      "certificates": {
        "total_certificates": 3,
        "recent_certificates": [],
        "trending_skills": [
          "Cloud Computing",
          "Data Science"
        ]
      },
      "activity": {
        "post_frequency": 3,
        "engagement_level": "Medium",
        "content_quality": "Moderate"
      },
      "type": "linkedin_url"
    },
    "analysis": {
      "overall_score": 80,
      "detailed_scores": {
        "certificates_and_skills": 20,
        "activity_and_engagement": 20,
        "professional_networking": 20,
        "profile_completeness": 20
      },
      "certificates_analysis": {
        "total_certificates": 3,
        "recent_certificates": [],
        "trending_skills": [
          "Cloud Computing",
          "Data Science"
        ]
      },
      "activity_analysis": {
        "post_frequency": 3,
        "engagement_level": "Medium",
        "content_quality": "Moderate"
      },
      "recommendations": [
        "Obtain recent certifications to show continuous learning",
        "Increase your posting frequency to improve visibility and engagement",
        "Share more professional content about your projects and achievements",
        "Share industry insights and thought leadership content",
        "Engage with others' posts through meaningful comments",
        "Update your profile regularly with new achievements",
        "Join relevant professional groups and participate in discussions"
      ]
    },
    "url": "https://www.linkedin.com/in/srimathi-s-2942a4292",
    "_id": "35ec217a-8289-42c8-8ec1-3937a506ff7c",
    "created_at": "2025-09-08T04:28:56.063944"
  },
  {
    "parsed_data": {
      "text": "SRIMATHI S Email : rajisrimathi2006@gmail.com\nlinkedin : linkedin.com/in/srimathi-s-2942a4292 Mobile : +91-6374164867\nProfessional Summary\nAspiring Full Stack Web Developer with hands-on experience in building responsive webapplications using HTML, CSS,\nJavaScript, React, Node.js, and MongoDB. Built and de-ployed projects like an online grocery shop and a personal\nportfolio. Eager to learn newtechnologies and solve real-world problems.\nEducation\n\u2022K.S. Rangasamy College of Technology, Tiruchengode Tamil Nadu, IN\nB.Tech in Computer Science and Business Systems (CSBS); CGPA: 7.9 (upto 3rd semester) August 2025 \u2013 Present\n\u2022Government Higher Secondary School, Periyapatti Tamil Nadu, IN\nHigher Secondary Certificate (HSC); Percentage: 72.5% 2022 \u2013 2023\n\u2022Government Higher Secondary School, Periyapatti Tamil Nadu, IN\nSecondary School Leaving Certificate (SSLC); Percentage: 100% 2020 \u2013 2021\nArea of Interest\n\u2022Technical Skills: HTML, CSS, JavaScript, React.js, Node.js, Express.js, MongoDB, MySQL, Power BI\n\u2022Soft Skills: Problem Solving, Communication, Team Collaboration, Adaptability\nExperience\n\u2022Personal Projects / Academic Work Tiruchengode, India (Remote)\nFull Stack Web Developer (Trainee) July 2025 \u2013 Present\n\u25e6Grocery Shop Website : Developed a full-stack grocery shopping website using HTML, CSS, JavaScript, React.js for the\nfrontend, and Node.js with MongoDB for backend. Included features like product listings, customer contact form, and admin\ndashboard.\n\u25e6Power BI : Developed and implemented a Spotify Dashboard using Power BI to visualize music data and insights.\n\u25e6Python + DBMS Academic Projects : Built mini-projects simulating real-time CRUD operations. Designed normalized\ndatabase schemas and performed SQL queries using MySQL.\n\u25e6Portfolio Website (Ongoing) : Building a personal portfolio using React.js and Tailwind CSS. Includes animated skill\nprogress bars, project showcase, contact section, and downloadable resume.\nCertifications / Personal Projects\n\u2022Certifications :\n\u25e6NPTEL Certification in Internet of Things (IoT) \u2013 Silver + Elite\n\u25e6NPTEL Certification in Python Programming\n\u25e6Infosys Certification in Python Full Stack Development\n\u25e6Infosys Certification in Java with Data Structures\n\u2022Personal Projects :\n\u25e6Grocery Shop Website \u2013 Full stack website built using React.js, Node.js, Express.js, and MongoDB. Includes product\nlisting, contact form, and admin dashboard.\n\u25e6Portfolio Website (In Progress) \u2013 Personal portfolio site using React.js and Tailwind CSS with animated skill bars and\ndownloadable resume.\n\u25e6Airline Reservation System (Java) \u2013 Simulates flight booking and management using object-oriented programming in\nJava.\n\u25e6Hospital Management System (DBMS) \u2013 CRUD-based database project implementing hospital records using MySQL\nand basic UI.",
      "email": "rajisrimathi2006@gmail.com",
      "phone": "+91-6374164867",
      "skills": [
        "Python",
        "JavaScript",
        "Java",
        "React",
        "Node.js",
        "SQL",
        "MongoDB",
        "HTML",
        "CSS",
        "Express",
        "MySQL"
      ],
      "education": [
        "CGPA: 7.9",
        "CGPA: 7.9",
        "Percentage: 72.5%",
        "Percentage: 72.5%",
        "B.Tech in Computer Science and Business Systems (CSBS); CGPA: 7.9 (upto 3rd semester) August 2025 \u2013 Present"
      ],
      "type": "resume"
    },
    "analysis": {
      "overall_score": 63.0,
      "detailed_scores": {
        "technical_score": 100,
        "experience_score": 0,
        "education_score": 65,
        "completeness_score": 100.0
      },
      "recommendations": [
        "Highlight more work experience and achievements"
      ]
    },
    "filename": "resume.pdf",
    "_id": "cd44aa07-ff0b-476c-9c23-d548d1379f03",
    "created_at": "2025-10-03T05:33:15.951304"
  },
  {
    "parsed_data": {
      "profile_url": "linkedin.com/in/srimathi-s-2942a4292",
      "certificates": {
        "total_certificates": 3,
        "recent_certificates": [],
        "trending_skills": [
          "Cloud Computing",
          "Data Science"
        ]
      },
      "activity": {
        "post_frequency": 3,
        "engagement_level": "Medium",
        "content_quality": "Moderate"
      },
      "type": "linkedin_url"
    },
    "analysis": {
      "overall_score": 80,
      "detailed_scores": {
        "certificates_and_skills": 20,
        "activity_and_engagement": 20,
        "professional_networking": 20,
        "profile_completeness": 20
      },
      "certificates_analysis": {
        "total_certificates": 3,
        "recent_certificates": [],
        "trending_skills": [
          "Cloud Computing",
          "Data Science"
        ]
      },
      "activity_analysis": {
        "post_frequency": 3,
        "engagement_level": "Medium",
        "content_quality": "Moderate"
      },
      "recommendations": [
        "Obtain recent certifications to show continuous learning",
        "Increase your posting frequency to improve visibility and engagement",
        "Share more professional content about your projects and achievements",
        "Create a custom LinkedIn URL for better professional branding",
        "Share industry insights and thought leadership content",
        "Engage with others' posts through meaningful comments",
        "Update your profile regularly with new achievements",
        "Join relevant professional groups and participate in discussions"
      ]
    },
    "url": "linkedin.com/in/srimathi-s-2942a4292",
    "_id": "17631c35-0b84-4d91-8df1-445ce24ab635",
    "created_at": "2025-10-03T05:34:47.447774"
  },
  {
    "parsed_data": {
      "text": "SRIMATHI S Email : rajisrimathi2006@gmail.com\nLinkedIn Mobile : +91-6374164867\nProfessional Summary\nAspiring Full Stack Web Developer with hands-on experience in building interactive web pages using HTML, CSS,\nJavaScript, and React.js. Familiar with backend development using Node.js and MongoDB, with strong academic\nexposure to Java programming and Database Management Systems (DBMS). Actively working on real-time projects such\nas an online grocery shop and a personal portfolio website. Eager to contribute to real-world development teams while\ncontinuously learning and improving backend and full stack capabilities. A fast learner with strong problem-solving skills\nand the ability to work independently or in collaborative environments.\nExperience\n\u2022Personal Projects / Academic Work Tiruchengode, India (Remote)\nFull Stack Web Developer (Trainee) July 2025 \u2013 Present\n\u25e6Grocery Shop Website : Developed a full-stack grocery shopping website using HTML, CSS, JavaScript, React.js for the\nfrontend, and Node.js with MongoDB for backend. Included features like product listings, customer contact form, and admin\ndashboard.\n\u25e6Power BI : Developed and implemented a Spotify Dashboard using Power BI to visualize music data and insights.\n\u25e6Python + DBMS Academic Projects : Built mini-projects simulating real-time CRUD operations. Designed normalized\ndatabase schemas and performed SQL queries using MySQL.\n\u25e6Portfolio Website (Ongoing) : Building a personal portfolio using React.js and Tailwind CSS. Includes animated skill\nprogress bars, project showcase, contact section, and downloadable resume.\nCertifications / Personal Projects\n\u2022Certifications :\n\u25e6NPTEL Certification in Internet of Things (IoT) \u2013 Silver + Elite\n\u25e6NPTEL Certification in Python Programming\n\u25e6Infosys Certification in Python Full Stack Development\n\u25e6Infosys Certification in Java with Data Structures\n\u25e6Web Development Bootcamp \u2013 Coursera\n\u25e6MongoDB Basics \u2013 Great Learning\n\u2022Personal Projects :\n\u25e6Grocery Shop Website \u2013 Full stack website built using React.js, Node.js, Express.js, and MongoDB. Includes product\nlisting, contact form, and admin dashboard.\n\u25e6Portfolio Website (In Progress) \u2013 Personal portfolio site using React.js and Tailwind CSS with animated skill bars and\ndownloadable resume.\n\u25e6Airline Reservation System (Java) \u2013 Simulates flight booking and management using object-oriented programming in\nJava.\n\u25e6Hospital Management System (DBMS) \u2013 CRUD-based database project implementing hospital records using MySQL\nand basic UI.\nEducation\n\u2022K.S. Rangasamy College of Technology, Tiruchengode Tamil Nadu, IN\nB.Tech in Computer Science and Business Systems (CSBS); CGPA: 8.0 (upto 3rd semester) August 2025 \u2013 Present\n\u2022Government Higher Secondary School, Periyapatti Tamil Nadu, IN\nHigher Secondary Certificate (HSC); Percentage: 72.5% 2022 \u2013 2023\n\u2022Government Higher Secondary School, Periyapatti Tamil Nadu, IN\nSecondary School Leaving Certificate (SSLC); Percentage: 100% 2020 \u2013 2021",
      "email": "rajisrimathi2006@gmail.com",
      "phone": "+91-6374164867",
      "skills": [
        "Python",
        "JavaScript",
        "Java",
        "React",
        "Node.js",
        "SQL",
        "MongoDB",
        "HTML",
        "CSS",
        "Express",
        "MySQL"
      ],
      "education": [
        "CGPA: 8.0",
        "CGPA: 8.0",
        "Percentage: 72.5%",
        "Percentage: 72.5%",
        "B.Tech in Computer Science and Business Systems (CSBS); CGPA: 8.0 (upto 3rd semester) August 2025 \u2013 Present"
      ],
      "type": "resume"
    },
    "analysis": {
      "overall_score": 64.0,
      "detailed_scores": {
        "technical_score": 100,
        "experience_score": 0,
        "education_score": 70,
        "completeness_score": 100.0
      },
      "recommendations": [
        "Highlight more work experience and achievements"
      ]
    },
    "filename": "resume2.pdf",
    "_id": "5a4a34c2-5772-409b-8663-9d7c3b797ddb",
    "created_at": "2025-11-09T11:12:37.118352"
  },
  {
    "parsed_data": {
      "text": "SRIMATHI S Email : rajisrimathi2006@gmail.com\nlinkedin : linkedin.com/in/srimathi-s-2942a4292 Mobile : +91-6374164867\nProfessional Summary\nAspiring Full Stack Web Developer with hands-on experience in building responsive webapplications using HTML, CSS,\nJavaScript, React, Node.js, and MongoDB. Built and de-ployed projects like an online grocery shop and a personal\nportfolio. Eager to learn newtechnologies and solve real-world problems.\nEducation\n\u2022K.S. Rangasamy College of Technology, Tiruchengode Tamil Nadu, IN\nB.Tech in Computer Science and Business Systems (CSBS); CGPA: 7.9 (upto 3rd semester) August 2025 \u2013 Present\n\u2022Government Higher Secondary School, Periyapatti Tamil Nadu, IN\nHigher Secondary Certificate (HSC); Percentage: 72.5% 2022 \u2013 2023\n\u2022Government Higher Secondary School, Periyapatti Tamil Nadu, IN\nSecondary School Leaving Certificate (SSLC); Percentage: 100% 2020 \u2013 2021\nArea of Interest\n\u2022Technical Skills: HTML, CSS, JavaScript, React.js, Node.js, Express.js, MongoDB, MySQL, Power BI\n\u2022Soft Skills: Problem Solving, Communication, Team Collaboration, Adaptability\nExperience\n\u2022Personal Projects / Academic Work Tiruchengode, India (Remote)\nFull Stack Web Developer (Trainee) July 2025 \u2013 Present\n\u25e6Grocery Shop Website : Developed a full-stack grocery shopping website using HTML, CSS, JavaScript, React.js for the\nfrontend, and Node.js with MongoDB for backend. Included features like product listings, customer contact form, and admin\ndashboard.\n\u25e6Power BI : Developed and implemented a Spotify Dashboard using Power BI to visualize music data and insights.\n\u25e6Python + DBMS Academic Projects : Built mini-projects simulating real-time CRUD operations. Designed normalized\ndatabase schemas and performed SQL queries using MySQL.\n\u25e6Portfolio Website (Ongoing) : Building a personal portfolio using React.js and Tailwind CSS. Includes animated skill\nprogress bars, project showcase, contact section, and downloadable resume.\nCertifications / Personal Projects\n\u2022Certifications :\n\u25e6NPTEL Certification in Internet of Things (IoT) \u2013 Silver + Elite\n\u25e6NPTEL Certification in Python Programming\n\u25e6Infosys Certification in Python Full Stack Development\n\u25e6Infosys Certification in Java with Data Structures\n\u2022Personal Projects :\n\u25e6Grocery Shop Website \u2013 Full stack website built using React.js, Node.js, Express.js, and MongoDB. Includes product\nlisting, contact form, and admin dashboard.\n\u25e6Portfolio Website (In Progress) \u2013 Personal portfolio site using React.js and Tailwind CSS with animated skill bars and\ndownloadable resume.\n\u25e6Airline Reservation System (Java) \u2013 Simulates flight booking and management using object-oriented programming in\nJava.\n\u25e6Hospital Management System (DBMS) \u2013 CRUD-based database project implementing hospital records using MySQL\nand basic UI.",
      "email": "rajisrimathi2006@gmail.com",
      "phone": "+91-6374164867",
      "skills": [
        "Python",
        "JavaScript",
        "Java",
        "React",
        "Node.js",
        "SQL",
        "MongoDB",
        "HTML",
        "CSS",
        "Express",
        "MySQL"
      ],
      "education": [
        "CGPA: 7.9",
        "CGPA: 7.9",
        "Percentage: 72.5%",
        "Percentage: 72.5%",
        "B.Tech in Computer Science and Business Systems (CSBS); CGPA: 7.9 (upto 3rd semester) August 2025 \u2013 Present"
      ],
      "type": "resume"
    },
    "analysis": {
      "overall_score": 63.0,
      "detailed_scores": {
        "technical_score": 100,
        "experience_score": 0,
        "education_score": 65,
        "completeness_score": 100.0
      },
      "recommendations": [
        "Highlight more work experience and achievements"
      ]
    },
    "filename": "resume.pdf",
    "_id": "7e4ca114-b470-4706-8cd4-58ed25a59509",
    "created_at": "2025-11-09T11:13:21.509152"
  },
  {
    "parsed_data": {
      "profile_url": "https://www.linkedin.com/in/srimathi-s-2942a4292",
      "certificates": {
        "total_certificates": 3,
        "recent_certificates": [],
        "trending_skills": [
          "Cloud Computing",
          "Data Science"
        ]
      },
      "activity": {
        "post_frequency": 3,
        "engagement_level": "Medium",
        "content_quality": "Moderate"
      },
      "type": "linkedin_url"
    },
    "analysis": {
      "overall_score": 80,
      "detailed_scores": {
        "certificates_and_skills": 20,
        "activity_and_engagement": 20,
        "professional_networking": 20,
        "profile_completeness": 20
      },
      "certificates_analysis": {
        "total_certificates": 3,
        "recent_certificates": [],
        "trending_skills": [
          "Cloud Computing",
          "Data Science"
        ]
      },
      "activity_analysis": {
        "post_frequency": 3,
        "engagement_level": "Medium",
        "content_quality": "Moderate"
      },
      "recommendations": [
        "Obtain recent certifications to show continuous learning",
        "Increase your posting frequency to improve visibility and engagement",
        "Share more professional content about your projects and achievements",
        "Share industry insights and thought leadership content",
        "Engage with others' posts through meaningful comments",
        "Update your profile regularly with new achievements",
        "Join relevant professional groups and participate in discussions"
      ]
    },
    "url": "https://www.linkedin.com/in/srimathi-s-2942a4292",
    "_id": "b79b62ea-6f57-4ac8-a5a7-9b46ff3006e8",
    "created_at": "2025-11-09T11:15:56.328643"
  },
  {
    "parsed_data": {
      "text": "SRIMATHI S Email : rajisrimathi2006@gmail.com\nlinkedin : linkedin.com/in/srimathi-s-2942a4292 Mobile : +91-6374164867\nProfessional Summary\nAspiring Full Stack Web Developer with hands-on experience in building responsive webapplications using HTML, CSS,\nJavaScript, React, Node.js, and MongoDB. Built and de-ployed projects like an online grocery shop and a personal\nportfolio. Eager to learn newtechnologies and solve real-world problems.\nEducation\n\u2022K.S. Rangasamy College of Technology, Tiruchengode Tamil Nadu, IN\nB.Tech in Computer Science and Business Systems (CSBS); CGPA: 7.9 (upto 3rd semester) August 2025 \u2013 Present\n\u2022Government Higher Secondary School, Periyapatti Tamil Nadu, IN\nHigher Secondary Certificate (HSC); Percentage: 72.5% 2022 \u2013 2023\n\u2022Government Higher Secondary School, Periyapatti Tamil Nadu, IN\nSecondary School Leaving Certificate (SSLC); Percentage: 100% 2020 \u2013 2021\nArea of Interest\n\u2022Technical Skills: HTML, CSS, JavaScript, React.js, Node.js, Express.js, MongoDB, MySQL, Power BI\n\u2022Soft Skills: Problem Solving, Communication, Team Collaboration, Adaptability\nExperience\n\u2022Personal Projects / Academic Work Tiruchengode, India (Remote)\nFull Stack Web Developer (Trainee) July 2025 \u2013 Present\n\u25e6Grocery Shop Website : Developed a full-stack grocery shopping website using HTML, CSS, JavaScript, React.js for the\nfrontend, and Node.js with MongoDB for backend. Included features like product listings, customer contact form, and admin\ndashboard.\n\u25e6Power BI : Developed and implemented a Spotify Dashboard using Power BI to visualize music data and insights.\n\u25e6Python + DBMS Academic Projects : Built mini-projects simulating real-time CRUD operations. Designed normalized\ndatabase schemas and performed SQL queries using MySQL.\n\u25e6Portfolio Website (Ongoing) : Building a personal portfolio using React.js and Tailwind CSS. Includes animated skill\nprogress bars, project showcase, contact section, and downloadable resume.\nCertifications / Personal Projects\n\u2022Certifications :\n\u25e6NPTEL Certification in Internet of Things (IoT) \u2013 Silver + Elite\n\u25e6NPTEL Certification in Python Programming\n\u25e6Infosys Certification in Python Full Stack Development\n\u25e6Infosys Certification in Java with Data Structures\n\u2022Personal Projects :\n\u25e6Grocery Shop Website \u2013 Full stack website built using React.js, Node.js, Express.js, and MongoDB. Includes product\nlisting, contact form, and admin dashboard.\n\u25e6Portfolio Website (In Progress) \u2013 Personal portfolio site using React.js and Tailwind CSS with animated skill bars and\ndownloadable resume.\n\u25e6Airline Reservation System (Java) \u2013 Simulates flight booking and management using object-oriented programming in\nJava.\n\u25e6Hospital Management System (DBMS) \u2013 CRUD-based database project implementing hospital records using MySQL\nand basic UI.",
      "email": "rajisrimathi2006@gmail.com",
      "phone": "+91-6374164867",
      "skills": [
        "Python",
        "JavaScript",
        "Java",
        "React",
        "Node.js",
        "SQL",
        "MongoDB",
        "HTML",
        "CSS",
        "Express",
        "MySQL"
      ],
      "education": [
        "CGPA: 7.9",
        "CGPA: 7.9",
        "Percentage: 72.5%",
        "Percentage: 72.5%",
        "B.Tech in Computer Science and Business Systems (CSBS); CGPA: 7.9 (upto 3rd semester) August 2025 \u2013 Present"
      ],
      "type": "resume"
    },
    "analysis": {
      "overall_score": 63.0,
      "detailed_scores": {
        "technical_score": 100,
        "experience_score": 0,
        "education_score": 65,
        "completeness_score": 100.0
      },
      "recommendations": [
        "Highlight more work experience and achievements"
      ]
    },
    "filename": "resume.pdf",
    "_id": "7e0a062d-90ed-4180-a3d3-8921af794bad",
    "created_at": "2025-11-09T11:20:06.095476"
  },
  {
    "parsed_data": {
      "profile_url": "https://www.linkedin.com/in/srimathi-s-2942a4292",
      "certificates": {
        "total_certificates": 3,
        "recent_certificates": [],
        "trending_skills": [
          "Cloud Computing",
          "Data Science"
        ]
      },
      "activity": {
        "post_frequency": 3,
        "engagement_level": "Medium",
        "content_quality": "Moderate"
      },
      "type": "linkedin_url"
    },
    "analysis": {
      "overall_score": 80,
      "detailed_scores": {
        "certificates_and_skills": 20,
        "activity_and_engagement": 20,
        "professional_networking": 20,
        "profile_completeness": 20
      },
      "certificates_analysis": {
        "total_certificates": 3,
        "recent_certificates": [],
        "trending_skills": [
          "Cloud Computing",
          "Data Science"
        ]
      },
      "activity_analysis": {
        "post_frequency": 3,
        "engagement_level": "Medium",
        "content_quality": "Moderate"
      },
      "recommendations": [
        "Obtain recent certifications to show continuous learning",
        "Increase your posting frequency to improve visibility and engagement",
        "Share more professional content about your projects and achievements",
        "Share industry insights and thought leadership content",
        "Engage with others' posts through meaningful comments",
        "Update your profile regularly with new achievements",
        "Join relevant professional groups and participate in discussions"
      ]
    },
    "url": "https://www.linkedin.com/in/srimathi-s-2942a4292",
    "_id": "77410d56-3d34-4e80-9ea3-18db82b5ec97",
    "created_at": "2025-11-09T11:25:44.667700"
  },
  {
    "parsed_data": {
      "text": "SRIMATHI S  \nJunior Developer | Passionate About Coding and Problem Solving  D/O SAMINATHAN G  D no. 2 -298 \nAranganoor,  Mettur, Salem - \n636451 +91 6374164867  \nrajisrimathi2006@gmail.com  \nSRIMATHI S | LinkedIn  \n \n  \nEDUCATION   \nGovernment Higher Secondary School, Periyapatti   \n  \nSSLC : 100% (2021)  \n  \nHSC : 72.5% (2023)  \nK S Rangasamy College of Technology, Tiruchengode   \nB Tech Computer Science and Bussiness Systems  \nCGPA : 7.9 upto third semester (2023 - 2027)  \nPROJECTS   \nHospital Management System(CRUD)  \u2013 Build using Python and SQL .  \nAirline Reservation System \u2013 Build using java.    \n  \nTOOLS  \n  \nCanva  \nFigma  \nKinemaster   \n SKILLS  \n Java Programming.  \n R Programming.  \n Basic Python.  \n SQL Programming.  \n Exel.  \n Git and Github.  \n Basic HTML and CSS.  \nAWARDS  \n  \nInfosys - Certified Java Developer.  \n  \nCodeathon at KPRIET.  \n  \nInfosys - Basic Python.   \n  \nI regularly engage in coding on \nplatforms such as Leetcode and \ngfg.  \n  \nLANGUAGES  \n  \nTamil and English \n ",
      "email": "rajisrimathi2006@gmail.com",
      "phone": "+91 6374164867",
      "skills": [
        "Python",
        "Java",
        "SQL",
        "Git",
        "HTML",
        "CSS"
      ],
      "education": [
        "CGPA: 7.9",
        "CGPA: 7.9",
        "Percentage: 72.5%"
      ],
      "type": "resume"
    },
    "analysis": {
      "overall_score": 45.0,
      "detailed_scores": {
        "technical_score": 60,
        "experience_score": 0,
        "education_score": 55,
        "completeness_score": 100.0
      },
      "recommendations": [
        "Highlight more work experience and achievements"
      ]
    },
    "filename": "Copy_of_Resume.pdf",
    "_id": "986ba554-8175-4ac6-bbcd-adc1145cac21",
    "created_at": "2025-12-11T14:33:51.211661"
  },
  {
    "parsed_data": {
      "profile_url": "https://www.linkedin.com/in/srimathi-s-2942a4292",
      "certificates": {
        "total_certificates": 3,
        "recent_certificates": [],
        "trending_skills": [
          "Cloud Computing",
          "Data Science"
        ]
      },
      "activity": {
        "post_frequency": 3,
        "engagement_level": "Medium",
        "content_quality": "Moderate"
      },
      "type": "linkedin_url"
    },
    "analysis": {
      "overall_score": 80,
      "detailed_scores": {
        "certificates_and_skills": 20,
        "activity_and_engagement": 20,
        "professional_networking": 20,
        "profile_completeness": 20
      },
      "certificates_analysis": {
        "total_certificates": 3,
        "recent_certificates": [],
        "trending_skills": [
          "Cloud Computing",
          "Data Science"
        ]
      },
      "activity_analysis": {
        "post_frequency": 3,
        "engagement_level": "Medium",
        "content_quality": "Moderate"
      },
      "recommendations": [
        "Obtain recent certifications to show continuous learning",
        "Increase your posting frequency to improve visibility and engagement",
        "Share more professional content about your projects and achievements",
        "Share industry insights and thought leadership content",
        "Engage with others' posts through meaningful comments",
        "Update your profile regularly with new achievements",
        "Join relevant professional groups and participate in discussions"
      ]
    },
    "url": "https://www.linkedin.com/in/srimathi-s-2942a4292",
    "_id": "037cf29e-38e4-4c63-99a4-68f2e15238f2",
    "created_at": "2025-12-12T05:43:11.189741"
  },
  {
    "parsed_data": {
      "text": "SRIMATHI S  \nJunior Developer | Passionate About Coding and Problem Solving  D/O SAMINATHAN G  D no. 2 -298 \nAranganoor,  Mettur, Salem - \n636451 +91 6374164867  \nrajisrimathi2006@gmail.com  \nSRIMATHI S | LinkedIn  \n \n  \nEDUCATION   \nGovernment Higher Secondary School, Periyapatti   \n  \nSSLC : 100% (2021)  \n  \nHSC : 72.5% (2023)  \nK S Rangasamy College of Technology, Tiruchengode   \nB Tech Computer Science and Bussiness Systems  \nCGPA : 7.9 upto third semester (2023 - 2027)  \nPROJECTS   \nHospital Management System(CRUD)  \u2013 Build using Python and SQL .  \nAirline Reservation System \u2013 Build using java.    \n  \nTOOLS  \n  \nCanva  \nFigma  \nKinemaster   \n SKILLS  \n Java Programming.  \n R Programming.  \n Basic Python.  \n SQL Programming.  \n Exel.  \n Git and Github.  \n Basic HTML and CSS.  \nAWARDS  \n  \nInfosys - Certified Java Developer.  \n  \nCodeathon at KPRIET.  \n  \nInfosys - Basic Python.   \n  \nI regularly engage in coding on \nplatforms such as Leetcode and \ngfg.  \n  \nLANGUAGES  \n  \nTamil and English \n ",
      "email": "rajisrimathi2006@gmail.com",
      "phone": "+91 6374164867",
      "skills": [
        "Python",
        "Java",
        "SQL",
        "Git",
        "HTML",
        "CSS"
      ],
      "education": [
        "CGPA: 7.9",
        "CGPA: 7.9",
        "Percentage: 72.5%"
      ],
      "type": "resume"
    },
    "analysis": {
      "overall_score": 45.0,
      "detailed_scores": {
        "technical_score": 60,
        "experience_score": 0,
        "education_score": 55,
        "completeness_score": 100.0
      },
      "recommendations": [
        "Highlight more work experience and achievements"
      ]
    },
    "filename": "Copy_of_Resume.pdf",
    "_id": "44b78d7d-7e10-4e84-980f-3fd2c95c27f7",
    "created_at": "2025-12-12T05:43:37.862713"
  },
  {
    "parsed_data": {
      "profile_url": "https://www.linkedin.com/in/srimathi-s-2942a4292",
      "certificates": {
        "total_certificates": 3,
        "recent_certificates": [],
        "trending_skills": [
          "Cloud Computing",
          "Data Science"
        ]
      },
      "activity": {
        "post_frequency": 3,
        "engagement_level": "Medium",
        "content_quality": "Moderate"
      },
      "type": "linkedin_url"
    },
    "analysis": {
      "overall_score": 80,
      "detailed_scores": {
        "certificates_and_skills": 20,
        "activity_and_engagement": 20,
        "professional_networking": 20,
        "profile_completeness": 20
      },
      "certificates_analysis": {
        "total_certificates": 3,
        "recent_certificates": [],
        "trending_skills": [
          "Cloud Computing",
          "Data Science"
        ]
      },
      "activity_analysis": {
        "post_frequency": 3,
        "engagement_level": "Medium",
        "content_quality": "Moderate"
      },
      "recommendations": [
        "Obtain recent certifications to show continuous learning",
        "Increase your posting frequency to improve visibility and engagement",
        "Share more professional content about your projects and achievements",
        "Share industry insights and thought leadership content",
        "Engage with others' posts through meaningful comments",
        "Update your profile regularly with new achievements",
        "Join relevant professional groups and participate in discussions"
      ]
    },
    "url": "https://www.linkedin.com/in/srimathi-s-2942a4292",
    "_id": "0487ee1d-ae3b-4132-97b9-288da3b4f4b9",
    "created_at": "2025-12-12T05:46:22.863730"
  },
  {
    "parsed_data": {
      "text": "SRIMATHI S  \nJunior Developer | Passionate About Coding and Problem Solving  D/O SAMINATHAN G  D no. 2 -298 \nAranganoor,  Mettur, Salem - \n636451 +91 6374164867  \nrajisrimathi2006@gmail.com  \nSRIMATHI S | LinkedIn  \n \n  \nEDUCATION   \nGovernment Higher Secondary School, Periyapatti   \n  \nSSLC : 100% (2021)  \n  \nHSC : 72.5% (2023)  \nK S Rangasamy College of Technology, Tiruchengode   \nB Tech Computer Science and Bussiness Systems  \nCGPA : 7.9 upto third semester (2023 - 2027)  \nPROJECTS   \nHospital Management System(CRUD)  \u2013 Build using Python and SQL .  \nAirline Reservation System \u2013 Build using java.    \n  \nTOOLS  \n  \nCanva  \nFigma  \nKinemaster   \n SKILLS  \n Java Programming.  \n R Programming.  \n Basic Python.  \n SQL Programming.  \n Exel.  \n Git and Github.  \n Basic HTML and CSS.  \nAWARDS  \n  \nInfosys - Certified Java Developer.  \n  \nCodeathon at KPRIET.  \n  \nInfosys - Basic Python.   \n  \nI regularly engage in coding on \nplatforms such as Leetcode and \ngfg.  \n  \nLANGUAGES  \n  \nTamil and English \n ",
      "email": "rajisrimathi2006@gmail.com",
      "phone": "+91 6374164867",
      "skills": [
        "Python",
        "Java",
        "SQL",
        "Git",
        "HTML",
        "CSS"
      ],
      "education": [
        "CGPA: 7.9",
        "CGPA: 7.9",
        "Percentage: 72.5%"
      ],
      "type": "resume"
    },
    "analysis": {
      "overall_score": 45.0,
      "detailed_scores": {
        "technical_score": 60,
        "experience_score": 0,
        "education_score": 55,
        "completeness_score": 100.0
      },
      "recommendations": [
        "Highlight more work experience and achievements"
      ]
    },
    "filename": "Copy_of_Resume.pdf",
    "_id": "894157f7-87b6-4486-a982-7d790bf40d1b",
    "created_at": "2025-12-12T05:48:00.924304"
  }
]